Workbook
Name AfterRetirement: 'Retirement planner'!$A1>=DesiredRetirementAge
Name Age: IF(PlanYear<=PlanYears,PlanYear-1+YourCurrentAge,NA())
Name AnnualPenionsBenefitsAtRetirement: 'Retirement planner'!$F$6
Name AnnualPensionBenefitAfterRetirementIncreasesPercentage: 'Retirement planner'!$F$7
Name AnnualPensionBenefitAmountUncertaintyPercentage: 'Retirement planner'!$I$9
Name AnnualPensionCenefitIncreasesUncertaintyPercentage: 'Retirement planner'!$I$10
Name AnnualSavingsAmountUncertaintyPercentage: 'Retirement planner'!$I$7
Name AnnualSavingsIncreasesUncertaintyPercentage: 'Retirement planner'!$I$8
Name Balance: IF(PlanYear<=PlanYears,Calculations!$H1048576,NA())
Name Balance_Over: IF(PlanYear<=PlanYears,Calculations!$T1048576,NA())
Name Balance_Under: IF(PlanYear<=PlanYears,Calculations!$N1048576,NA())
Name BeforeRetirement: 'Retirement planner'!$A1<DesiredRetirementAge
Name ColumnTitleRegion1..I114.1: 'Retirement planner'!$A$15
Name CurrentAnnualIncome: 'Retirement planner'!$C$7
Name CurrentAnnualIncomeIncreasesPercentage: 'Retirement planner'!$C$8
Name CurrentAnnualSavingsAmount: 'Retirement planner'!$C$10
Name CurrentAnnualSavingsAmount_Over: CurrentAnnualSavingsAmount+CurrentAnnualSavingsAmount*AnnualSavingsAmountUncertaintyPercentage/2
Name CurrentAnnualSavingsAmount_Under: CurrentAnnualSavingsAmount-CurrentAnnualSavingsAmount*AnnualSavingsAmountUncertaintyPercentage/2
Name CurrentAnnualSavingsIncreasesPercentage: 'Retirement planner'!$C$11
Name CurrentRetirementSavingsBalance: 'Retirement planner'!$C$9
Name DesiredRetirementAge: 'Retirement planner'!$F$8
Name DesiredRetirementIncome: IF(PlanYear<=PlanYears,AfterRetirement*IncomeReplacementAtRetirementPercentage*CurrentAnnualIncome*(1+CurrentAnnualIncomeIncreasesPercentage)^(Calculations!$A1-Calculations!$A$16),NA())
Name EndBalance: IF(PlanYear<=PlanYears,Calculations!XEZ1+Calculations!XFA1+Calculations!XFB1-Calculations!XFC1+Calculations!XFD1,NA())
Name IncomeReplacementAtRetirementPercentage: 'Retirement planner'!$F$10
Name Interest: IF(PlanYear<=PlanYears,(Calculations!XFD1*BeforeRetirement*InvestmentReturnPreRetirementPercentage)+(Calculations!XFD1*AfterRetirement*InvestmentReturnPostRetirementPercentage),NA())
Name InvestmentReturnPostRetirementPercentage: 'Retirement planner'!$F$11
Name InvestmentReturnPreRetirementPercentage: 'Retirement planner'!$C$12
Name InvestmentReturnUncertaintyPercentage: 'Retirement planner'!$I$6
Name LastRow: COUNTIF('Retirement planner'!$A$15:$A$115,">1")+35
Name PensionIncome: IF(PlanYear<=PlanYears,AfterRetirement*PensionIncomeInflated,NA())
Name PensionIncome_Over: IF(PlanYear<=PlanYears,AfterRetirement*PensionIncomeInflated_Over,NA())
Name PensionIncome_Under: IF(PlanYear<=PlanYears,AfterRetirement*PensionIncomeInflated_Under,NA())
Name PensionIncomeInflated: AnnualPenionsBenefitsAtRetirement*(1+AnnualPensionBenefitAfterRetirementIncreasesPercentage)^(Calculations!$A1-DesiredRetirementAge)
Name PlanYear: ROWS(Calculations!$A$16:$A1)
Name PlanYears: YearsOfRetirementIncome+(DesiredRetirementAge-YourCurrentAge)
Name Print_Area_Reset: OFFSET('Retirement planner'!$A$1:$J$115,0,0,LastRow)
Name ResultsDisplay_Failure: Calculations!$H$6
Name ResultsDisplay_Failure_1: Calculations!$H$9
Name ResultsDisplay_Failure_2: Calculations!$H$10
Name ResultsDisplay_Failure_3: Calculations!$H$11
Name ResultsDisplay_Failure_4: Calculations!$H$12
Name ResultsDisplay_Success: Calculations!$H$7
Name ResultsDisplay_Success_1: Calculations!$F$9
Name ResultsDisplay_Success_2: Calculations!$F$10
Name ResultsDisplay_Success_3: Calculations!$F$11
Name ResultsDisplay_Success_4: Calculations!$F$12
Name ResultsDisplay_Success_5: Calculations!$F$13
Name RowTitleRegion1..D12: 'Retirement planner'!$A$6
Name RowTitleRegion2..G11: 'Retirement planner'!$D$6
Name RowTitleRegion3..J10: 'Retirement planner'!$G$6
Name Salary: IF(PlanYear<=PlanYears,BeforeRetirement*(Calculations!$B1048576+Calculations!$B1048576*CurrentAnnualIncomeIncreasesPercentage),NA())
Name SavingsBalance_Disbursements: Calculations!$F$16:INDEX(Calculations!$F$16:$F$115,PlanYears)
Name SavingsBalance_RetiredPeriod: Calculations!$X$16:INDEX(Calculations!$X$16:$X$115,PlanYears)
Name SavingsBalance_WorkingPeriod: Calculations!$W$16:INDEX(Calculations!$W$16:$W$115,PlanYears)
Name Success: Calculations!$D$8
Name UncertaintyCone_Over: Calculations!$AA$16:INDEX(Calculations!$AA$16:$AA$115,PlanYears)
Name UncertaintyCone_Under: Calculations!$N$16:INDEX(Calculations!$N$16:$N$115,PlanYears)
Name YearlySavings: IF(PlanYear<=PlanYears,BeforeRetirement*YearlySavingsInflated,NA())
Name YearlySavings_Over: IF(PlanYear<=PlanYears,BeforeRetirement*YearlySavingsInflated_Over,NA())
Name YearlySavings_Under: IF(PlanYear<=PlanYears,BeforeRetirement*YearlySavingsInflated_Under,NA())

Sheet Retirement planner
A1: Retirement planner
A2: =IF(INDEX(SavingsBalance_RetiredPeriod,PlanYears)>=0,CONCATENATE(ResultsDisplay_Success_1," ",ResultsDisplay_Success_2, " ",ResultsDisplay_Success_3," ",ResultsDisplay_Success_4," ",ResultsDisplay_Success_5),CONCATENATE(ResultsDisplay_Failure_1," ",ResultsDisplay_Failure_2," ",ResultsDisplay_Failure_3," ",ResultsDisplay_Failure_4)) -> Congratulations! At age 84, you will have a savings balance of $1,164,874.
A4: Input
B5: Now | C5: Amount | D5: At Retirement | F5: Amount | G5: Uncertainty (%) | I5: Amount
B6: Your current age | C6: 25 | D6: Annual pension benefit ($) | F6: 42000 | G6: Investment return uncertainty | I6: 0.02
B7: Annual income ($) | C7: 50000 | D7: Annual pension benefit increases (%) | F7: 0 | G7: Annual savings amount uncertainty | I7: 0
B8: Annual inflation & income increases (%) | C8: 0.01 | D8: Desired retirement age | F8: 65 | G8: Annual savings increases uncertainty | I8: 0
B9: Retirement savings balance ($) | C9: 0 | D9: Number of years of retirement income | F9: 20 | G9: Annual pension benefit amount uncertainty | I9: 0
B10: Annual savings amount ($) | C10: 6000 | D10: Income replacement (%) | F10: 0.75 | G10: Annual Pension benefit increases uncertainty | I10: 0
B11: Annual savings increases (%) | C11: 0 | D11: Investment return (%) | F11: 0.045
B12: Investment return (%) | C12: 0.05
A14: Chart details
A15: Age | B15: Salary | C15: Balance | D15: Interest | E15: Yearly savings | F15: Desired retirement income | G15: Pension income | H15: Year ending balance
A16: =IFERROR(Calculations!A16,"") -> 25 | B16: =IFERROR(Calculations!B16,"") -> 50000 | C16: =IFERROR(Calculations!C16,"") -> 0 | D16: =IFERROR(Calculations!D16,"") -> 0 | E16: =IFERROR(Calculations!E16,"") -> 6000 | F16: =IFERROR(Calculations!F16,"") -> 0 | G16: =IFERROR(Calculations!G16,"") -> 0 | H16: =IFERROR(Calculations!H16,"") -> 6000
A17: =IFERROR(Calculations!A17,"") -> 26 | B17: =IFERROR(Calculations!B17,"") -> 50500 | C17: =IFERROR(Calculations!C17,"") -> 6000 | D17: =IFERROR(Calculations!D17,"") -> 300 | E17: =IFERROR(Calculations!E17,"") -> 6000 | F17: =IFERROR(Calculations!F17,"") -> 0 | G17: =IFERROR(Calculations!G17,"") -> 0 | H17: =IFERROR(Calculations!H17,"") -> 12300
A18: =IFERROR(Calculations!A18,"") -> 27 | B18: =IFERROR(Calculations!B18,"") -> 51005 | C18: =IFERROR(Calculations!C18,"") -> 12300 | D18: =IFERROR(Calculations!D18,"") -> 615 | E18: =IFERROR(Calculations!E18,"") -> 6000 | F18: =IFERROR(Calculations!F18,"") -> 0 | G18: =IFERROR(Calculations!G18,"") -> 0 | H18: =IFERROR(Calculations!H18,"") -> 18915
A19: =IFERROR(Calculations!A19,"") -> 28 | B19: =IFERROR(Calculations!B19,"") -> 51515.05 | C19: =IFERROR(Calculations!C19,"") -> 18915 | D19: =IFERROR(Calculations!D19,"") -> 945.75 | E19: =IFERROR(Calculations!E19,"") -> 6000 | F19: =IFERROR(Calculations!F19,"") -> 0 | G19: =IFERROR(Calculations!G19,"") -> 0 | H19: =IFERROR(Calculations!H19,"") -> 25860.75
A20: =IFERROR(Calculations!A20,"") -> 29 | B20: =IFERROR(Calculations!B20,"") -> 52030.201 | C20: =IFERROR(Calculations!C20,"") -> 25860.75 | D20: =IFERROR(Calculations!D20,"") -> 1293.0375 | E20: =IFERROR(Calculations!E20,"") -> 6000 | F20: =IFERROR(Calculations!F20,"") -> 0 | G20: =IFERROR(Calculations!G20,"") -> 0 | H20: =IFERROR(Calculations!H20,"") -> 33153.787
A21: =IFERROR(Calculations!A21,"") -> 30 | B21: =IFERROR(Calculations!B21,"") -> 52550.503 | C21: =IFERROR(Calculations!C21,"") -> 33153.787 | D21: =IFERROR(Calculations!D21,"") -> 1657.6894 | E21: =IFERROR(Calculations!E21,"") -> 6000 | F21: =IFERROR(Calculations!F21,"") -> 0 | G21: =IFERROR(Calculations!G21,"") -> 0 | H21: =IFERROR(Calculations!H21,"") -> 40811.477
A22: =IFERROR(Calculations!A22,"") -> 31 | B22: =IFERROR(Calculations!B22,"") -> 53076.008 | C22: =IFERROR(Calculations!C22,"") -> 40811.477 | D22: =IFERROR(Calculations!D22,"") -> 2040.5738 | E22: =IFERROR(Calculations!E22,"") -> 6000 | F22: =IFERROR(Calculations!F22,"") -> 0 | G22: =IFERROR(Calculations!G22,"") -> 0 | H22: =IFERROR(Calculations!H22,"") -> 48852.051
A23: =IFERROR(Calculations!A23,"") -> 32 | B23: =IFERROR(Calculations!B23,"") -> 53606.768 | C23: =IFERROR(Calculations!C23,"") -> 48852.051 | D23: =IFERROR(Calculations!D23,"") -> 2442.6025 | E23: =IFERROR(Calculations!E23,"") -> 6000 | F23: =IFERROR(Calculations!F23,"") -> 0 | G23: =IFERROR(Calculations!G23,"") -> 0 | H23: =IFERROR(Calculations!H23,"") -> 57294.653
A24: =IFERROR(Calculations!A24,"") -> 33 | B24: =IFERROR(Calculations!B24,"") -> 54142.835 | C24: =IFERROR(Calculations!C24,"") -> 57294.653 | D24: =IFERROR(Calculations!D24,"") -> 2864.7327 | E24: =IFERROR(Calculations!E24,"") -> 6000 | F24: =IFERROR(Calculations!F24,"") -> 0 | G24: =IFERROR(Calculations!G24,"") -> 0 | H24: =IFERROR(Calculations!H24,"") -> 66159.386
A25: =IFERROR(Calculations!A25,"") -> 34 | B25: =IFERROR(Calculations!B25,"") -> 54684.264 | C25: =IFERROR(Calculations!C25,"") -> 66159.386 | D25: =IFERROR(Calculations!D25,"") -> 3307.9693 | E25: =IFERROR(Calculations!E25,"") -> 6000 | F25: =IFERROR(Calculations!F25,"") -> 0 | G25: =IFERROR(Calculations!G25,"") -> 0 | H25: =IFERROR(Calculations!H25,"") -> 75467.355
A26: =IFERROR(Calculations!A26,"") -> 35 | B26: =IFERROR(Calculations!B26,"") -> 55231.106 | C26: =IFERROR(Calculations!C26,"") -> 75467.355 | D26: =IFERROR(Calculations!D26,"") -> 3773.3678 | E26: =IFERROR(Calculations!E26,"") -> 6000 | F26: =IFERROR(Calculations!F26,"") -> 0 | G26: =IFERROR(Calculations!G26,"") -> 0 | H26: =IFERROR(Calculations!H26,"") -> 85240.723
A27: =IFERROR(Calculations!A27,"") -> 36 | B27: =IFERROR(Calculations!B27,"") -> 55783.417 | C27: =IFERROR(Calculations!C27,"") -> 85240.723 | D27: =IFERROR(Calculations!D27,"") -> 4262.0361 | E27: =IFERROR(Calculations!E27,"") -> 6000 | F27: =IFERROR(Calculations!F27,"") -> 0 | G27: =IFERROR(Calculations!G27,"") -> 0 | H27: =IFERROR(Calculations!H27,"") -> 95502.759
... A115: =IFERROR(Calculations!A115,"") | B115: =IFERROR(Calculations!B115,"") | C115: =IFERROR(Calculations!C115,"") | D115: =IFERROR(Calculations!D115,"") | E115: =IFERROR(Calculations!E115,"") | F115: =IFERROR(Calculations!F115,"") | G115: =IFERROR(Calculations!G115,"") | H115: =IFERROR(Calculations!H115,"")

Sheet Calculations
A1: Calculations
A2: This sheet should remain hidden. Any modifications may result in errors in the retirement planner.
E3: {=INDEX(A16:A115,MATCH(MIN(IF(ISNUMBER(SavingsBalance_RetiredPeriod),IF((SavingsBalance_RetiredPeriod>0),SavingsBalance_RetiredPeriod))),SavingsBalance_RetiredPeriod,0))} -> 64 | F3: Failure template: | H3: Oops. This plan will only provide income to age [AGE]. You'll need to make some modifications.
D4: =TEXT(INDEX(SavingsBalance_RetiredPeriod,PlanYears),"$#,###") -> $1,164,874 | E4: =YourCurrentAge+PlanYears-1 -> 84 | F4: Success template: | H4: Congratulations! Your plan seems to work. At age [AGE], you will still have a savings balance of [BALANCE].
E6: =INDEX($E$3:$E$4,(INDEX(SavingsBalance_RetiredPeriod,PlanYears)>0)+1) -> 84 | F6: Failure display: | H6: =REPT(SUBSTITUTE(SUBSTITUTE(H3,"[AGE]",$E$6),"[BALANCE]",$D$4),INDEX(SavingsBalance_RetiredPeriod,PlanYears)<0)
E7: =INDEX($E$3:$E$4,(INDEX(SavingsBalance_RetiredPeriod,PlanYears)>0)+1) -> 84 | F7: Success display: | H7: =REPT(SUBSTITUTE(SUBSTITUTE(H4,"[AGE]",$E$6),"[BALANCE]",$D$4),INDEX(SavingsBalance_RetiredPeriod,PlanYears)>=0) -> Congratulations! Your plan seems to work. At age 84, you will still have a savings balance of $1,164,874.
C8: Success: | D8: =INDEX(SavingsBalance_RetiredPeriod,PlanYears)>=0 -> TRUE | F8: Success | H8: Failure
E9: 1 | F9: =REPT("Congratulations!",Success) -> Congratulations! | H9: =REPT("OOPS!",Success=FALSE)
E10: 2 | F10: =REPT("At age",Success) -> At age | H10: =REPT("This plan will only provide income to age",Success=FALSE)
E11: 3 | F11: =REPT(YourCurrentAge+PlanYears-1 & ",",Success) -> 84, | H11: =REPT(E3 & ".",Success=FALSE)
E12: 4 | F12: =REPT("you will have a savings balance of",Success) -> you will have a savings balance of | H12: =REPT("You'll need to make some adjustments.",Success=FALSE)
E13: 5 | F13: =REPT(TEXT(INDEX(SavingsBalance_RetiredPeriod,PlanYears),"$#,###."),Success) -> $1,164,874.
A15: Age | B15: Salary | C15: Balance | D15: Interest | E15: Yearly savings | F15: Desired retirement income | G15: Pension income | H15: End balance | I15: Balance | J15: Interest | K15: Yearly savings | L15: Desired retirement income | M15: Pension income | N15: End balance | O15: Balance | P15: Interest | Q15: Yearly savings | R15: Desired retirement income | S15: Pension income | T15: End balance | W15: Saving | X15: Retired | AA15: Uncertainty
A16: =Age -> 25 | B16: =CurrentAnnualIncome -> 50000 | C16: =CurrentRetirementSavingsBalance -> 0 | D16: =IFERROR(Interest,"") -> 0 | E16: =CurrentAnnualSavingsAmount -> 6000 | F16: =IFERROR(DesiredRetirementIncome,"") -> 0 | G16: =IFERROR(PensionIncome,"") -> 0 | H16: =IFERROR(EndBalance,"") -> 6000 | I16: =CurrentRetirementSavingsBalance -> 0 | J16: =IFERROR(Interest_Under,"") -> 0 | K16: =CurrentAnnualSavingsAmount_Under -> 6000 | L16: =IFERROR(DesiredRetirementIncome,"") -> 0 | M16: =IFERROR(PensionIncome_Under,"") -> 0 | N16: =IFERROR(EndBalance,"") -> 6000 | O16: =CurrentRetirementSavingsBalance -> 0 | P16: =IFERROR(Interest_Over,"") -> 0 | Q16: =CurrentAnnualSavingsAmount_Over -> 6000 | R16: =IFERROR(DesiredRetirementIncome,"") -> 0 | S16: =IFERROR(PensionIncome_Over,"") -> 0 | T16: =IFERROR(EndBalance,"") -> 6000 | W16: =IF(Calculations!A16<DesiredRetirementAge,H16,NA()) -> 6000 | X16: =IF(Calculations!A16>=(DesiredRetirementAge-1),H16,NA()) -> #N/A | AA16: =T16-N16 -> 0
A17: =IFERROR(Age,"") -> 26 | B17: =IFERROR(Salary,"") -> 50500 | C17: =IFERROR(Balance,"") -> 6000 | D17: =IFERROR(Interest,"") -> 300 | E17: =IFERROR(YearlySavings,"") -> 6000 | F17: =IFERROR(DesiredRetirementIncome,"") -> 0 | G17: =IFERROR(PensionIncome,"") -> 0 | H17: =IFERROR(EndBalance,"") -> 12300 | I17: =IFERROR(Balance_Under,"") -> 6000 | J17: =IFERROR(Interest_Under,"") -> 240 | K17: =IFERROR(YearlySavings_Under,"") -> 6000 | L17: =IFERROR(DesiredRetirementIncome,"") -> 0 | M17: =IFERROR(PensionIncome_Under,"") -> 0 | N17: =IFERROR(EndBalance,"") -> 12240 | O17: =IFERROR(Balance_Over,"") -> 6000 | P17: =IFERROR(Interest_Over,"") -> 360 | Q17: =IFERROR(YearlySavings_Over,"") -> 6000 | R17: =IFERROR(DesiredRetirementIncome,"") -> 0 | S17: =IFERROR(PensionIncome_Over,"") -> 0 | T17: =IFERROR(EndBalance,"") -> 12360 | W17: =IF(Calculations!A17<DesiredRetirementAge,H17,NA()) -> 12300 | X17: =IF(Calculations!A17>=(DesiredRetirementAge-1),H17,NA()) -> #N/A | AA17: =T17-N17 -> 120
A18: =IFERROR(Age,"") -> 27 | B18: =IFERROR(Salary,"") -> 51005 | C18: =IFERROR(Balance,"") -> 12300 | D18: =IFERROR(Interest,"") -> 615 | E18: =IFERROR(YearlySavings,"") -> 6000 | F18: =IFERROR(DesiredRetirementIncome,"") -> 0 | G18: =IFERROR(PensionIncome,"") -> 0 | H18: =IFERROR(EndBalance,"") -> 18915 | I18: =IFERROR(Balance_Under,"") -> 12240 | J18: =IFERROR(Interest_Under,"") -> 489.6 | K18: =IFERROR(YearlySavings_Under,"") -> 6000 | L18: =IFERROR(DesiredRetirementIncome,"") -> 0 | M18: =IFERROR(PensionIncome_Under,"") -> 0 | N18: =IFERROR(EndBalance,"") -> 18729.6 | O18: =IFERROR(Balance_Over,"") -> 12360 | P18: =IFERROR(Interest_Over,"") -> 741.6 | Q18: =IFERROR(YearlySavings_Over,"") -> 6000 | R18: =IFERROR(DesiredRetirementIncome,"") -> 0 | S18: =IFERROR(PensionIncome_Over,"") -> 0 | T18: =IFERROR(EndBalance,"") -> 19101.6 | W18: =IF(Calculations!A18<DesiredRetirementAge,H18,NA()) -> 18915 | X18: =IF(Calculations!A18>=(DesiredRetirementAge-1),H18,NA()) -> #N/A | AA18: =T18-N18 -> 372
A19: =IFERROR(Age,"") -> 28 | B19: =IFERROR(Salary,"") -> 51515.05 | C19: =IFERROR(Balance,"") -> 18915 | D19: =IFERROR(Interest,"") -> 945.75 | E19: =IFERROR(YearlySavings,"") -> 6000 | F19: =IFERROR(DesiredRetirementIncome,"") -> 0 | G19: =IFERROR(PensionIncome,"") -> 0 | H19: =IFERROR(EndBalance,"") -> 25860.75 | I19: =IFERROR(Balance_Under,"") -> 18729.6 | J19: =IFERROR(Interest_Under,"") -> 749.184 | K19: =IFERROR(YearlySavings_Under,"") -> 6000 | L19: =IFERROR(DesiredRetirementIncome,"") -> 0 | M19: =IFERROR(PensionIncome_Under,"") -> 0 | N19: =IFERROR(EndBalance,"") -> 25478.784 | O19: =IFERROR(Balance_Over,"") -> 19101.6 | P19: =IFERROR(Interest_Over,"") -> 1146.096 | Q19: =IFERROR(YearlySavings_Over,"") -> 6000 | R19: =IFERROR(DesiredRetirementIncome,"") -> 0 | S19: =IFERROR(PensionIncome_Over,"") -> 0 | T19: =IFERROR(EndBalance,"") -> 26247.696 | W19: =IF(Calculations!A19<DesiredRetirementAge,H19,NA()) -> 25860.75 | X19: =IF(Calculations!A19>=(DesiredRetirementAge-1),H19,NA()) -> #N/A | AA19: =T19-N19 -> 768.912
A20: =IFERROR(Age,"") -> 29 | B20: =IFERROR(Salary,"") -> 52030.201 | C20: =IFERROR(Balance,"") -> 25860.75 | D20: =IFERROR(Interest,"") -> 1293.0375 | E20: =IFERROR(YearlySavings,"") -> 6000 | F20: =IFERROR(DesiredRetirementIncome,"") -> 0 | G20: =IFERROR(PensionIncome,"") -> 0 | H20: =IFERROR(EndBalance,"") -> 33153.787 | I20: =IFERROR(Balance_Under,"") -> 25478.784 | J20: =IFERROR(Interest_Under,"") -> 1019.1514 | K20: =IFERROR(YearlySavings_Under,"") -> 6000 | L20: =IFERROR(DesiredRetirementIncome,"") -> 0 | M20: =IFERROR(PensionIncome_Under,"") -> 0 | N20: =IFERROR(EndBalance,"") -> 32497.935 | O20: =IFERROR(Balance_Over,"") -> 26247.696 | P20: =IFERROR(Interest_Over,"") -> 1574.8618 | Q20: =IFERROR(YearlySavings_Over,"") -> 6000 | R20: =IFERROR(DesiredRetirementIncome,"") -> 0 | S20: =IFERROR(PensionIncome_Over,"") -> 0 | T20: =IFERROR(EndBalance,"") -> 33822.558 | W20: =IF(Calculations!A20<DesiredRetirementAge,H20,NA()) -> 33153.787 | X20: =IF(Calculations!A20>=(DesiredRetirementAge-1),H20,NA()) -> #N/A | AA20: =T20-N20 -> 1324.6224
A21: =IFERROR(Age,"") -> 30 | B21: =IFERROR(Salary,"") -> 52550.503 | C21: =IFERROR(Balance,"") -> 33153.787 | D21: =IFERROR(Interest,"") -> 1657.6894 | E21: =IFERROR(YearlySavings,"") -> 6000 | F21: =IFERROR(DesiredRetirementIncome,"") -> 0 | G21: =IFERROR(PensionIncome,"") -> 0 | H21: =IFERROR(EndBalance,"") -> 40811.477 | I21: =IFERROR(Balance_Under,"") -> 32497.935 | J21: =IFERROR(Interest_Under,"") -> 1299.9174 | K21: =IFERROR(YearlySavings_Under,"") -> 6000 | L21: =IFERROR(DesiredRetirementIncome,"") -> 0 | M21: =IFERROR(PensionIncome_Under,"") -> 0 | N21: =IFERROR(EndBalance,"") -> 39797.853 | O21: =IFERROR(Balance_Over,"") -> 33822.558 | P21: =IFERROR(Interest_Over,"") -> 2029.3535 | Q21: =IFERROR(YearlySavings_Over,"") -> 6000 | R21: =IFERROR(DesiredRetirementIncome,"") -> 0 | S21: =IFERROR(PensionIncome_Over,"") -> 0 | T21: =IFERROR(EndBalance,"") -> 41851.911 | W21: =IF(Calculations!A21<DesiredRetirementAge,H21,NA()) -> 40811.477 | X21: =IF(Calculations!A21>=(DesiredRetirementAge-1),H21,NA()) -> #N/A | AA21: =T21-N21 -> 2054.0585
A22: =IFERROR(Age,"") -> 31 | B22: =IFERROR(Salary,"") -> 53076.008 | C22: =IFERROR(Balance,"") -> 40811.477 | D22: =IFERROR(Interest,"") -> 2040.5738 | E22: =IFERROR(YearlySavings,"") -> 6000 | F22: =IFERROR(DesiredRetirementIncome,"") -> 0 | G22: =IFERROR(PensionIncome,"") -> 0 | H22: =IFERROR(EndBalance,"") -> 48852.051 | I22: =IFERROR(Balance_Under,"") -> 39797.853 | J22: =IFERROR(Interest_Under,"") -> 1591.9141 | K22: =IFERROR(YearlySavings_Under,"") -> 6000 | L22: =IFERROR(DesiredRetirementIncome,"") -> 0 | M22: =IFERROR(PensionIncome_Under,"") -> 0 | N22: =IFERROR(EndBalance,"") -> 47389.767 | O22: =IFERROR(Balance_Over,"") -> 41851.911 | P22: =IFERROR(Interest_Over,"") -> 2511.1147 | Q22: =IFERROR(YearlySavings_Over,"") -> 6000 | R22: =IFERROR(DesiredRetirementIncome,"") -> 0 | S22: =IFERROR(PensionIncome_Over,"") -> 0 | T22: =IFERROR(EndBalance,"") -> 50363.026 | W22: =IF(Calculations!A22<DesiredRetirementAge,H22,NA()) -> 48852.051 | X22: =IF(Calculations!A22>=(DesiredRetirementAge-1),H22,NA()) -> #N/A | AA22: =T22-N22 -> 2973.259
A23: =IFERROR(Age,"") -> 32 | B23: =IFERROR(Salary,"") -> 53606.768 | C23: =IFERROR(Balance,"") -> 48852.051 | D23: =IFERROR(Interest,"") -> 2442.6025 | E23: =IFERROR(YearlySavings,"") -> 6000 | F23: =IFERROR(DesiredRetirementIncome,"") -> 0 | G23: =IFERROR(PensionIncome,"") -> 0 | H23: =IFERROR(EndBalance,"") -> 57294.653 | I23: =IFERROR(Balance_Under,"") -> 47389.767 | J23: =IFERROR(Interest_Under,"") -> 1895.5907 | K23: =IFERROR(YearlySavings_Under,"") -> 6000 | L23: =IFERROR(DesiredRetirementIncome,"") -> 0 | M23: =IFERROR(PensionIncome_Under,"") -> 0 | N23: =IFERROR(EndBalance,"") -> 55285.358 | O23: =IFERROR(Balance_Over,"") -> 50363.026 | P23: =IFERROR(Interest_Over,"") -> 3021.7816 | Q23: =IFERROR(YearlySavings_Over,"") -> 6000 | R23: =IFERROR(DesiredRetirementIncome,"") -> 0 | S23: =IFERROR(PensionIncome_Over,"") -> 0 | T23: =IFERROR(EndBalance,"") -> 59384.807 | W23: =IF(Calculations!A23<DesiredRetirementAge,H23,NA()) -> 57294.653 | X23: =IF(Calculations!A23>=(DesiredRetirementAge-1),H23,NA()) -> #N/A | AA23: =T23-N23 -> 4099.4499
A24: =IFERROR(Age,"") -> 33 | B24: =IFERROR(Salary,"") -> 54142.835 | C24: =IFERROR(Balance,"") -> 57294.653 | D24: =IFERROR(Interest,"") -> 2864.7327 | E24: =IFERROR(YearlySavings,"") -> 6000 | F24: =IFERROR(DesiredRetirementIncome,"") -> 0 | G24: =IFERROR(PensionIncome,"") -> 0 | H24: =IFERROR(EndBalance,"") -> 66159.386 | I24: =IFERROR(Balance_Under,"") -> 55285.358 | J24: =IFERROR(Interest_Under,"") -> 2211.4143 | K24: =IFERROR(YearlySavings_Under,"") -> 6000 | L24: =IFERROR(DesiredRetirementIncome,"") -> 0 | M24: =IFERROR(PensionIncome_Under,"") -> 0 | N24: =IFERROR(EndBalance,"") -> 63496.772 | O24: =IFERROR(Balance_Over,"") -> 59384.807 | P24: =IFERROR(Interest_Over,"") -> 3563.0884 | Q24: =IFERROR(YearlySavings_Over,"") -> 6000 | R24: =IFERROR(DesiredRetirementIncome,"") -> 0 | S24: =IFERROR(PensionIncome_Over,"") -> 0 | T24: =IFERROR(EndBalance,"") -> 68947.896 | W24: =IF(Calculations!A24<DesiredRetirementAge,H24,NA()) -> 66159.386 | X24: =IF(Calculations!A24>=(DesiredRetirementAge-1),H24,NA()) -> #N/A | AA24: =T24-N24 -> 5451.124
A25: =IFERROR(Age,"") -> 34 | B25: =IFERROR(Salary,"") -> 54684.264 | C25: =IFERROR(Balance,"") -> 66159.386 | D25: =IFERROR(Interest,"") -> 3307.9693 | E25: =IFERROR(YearlySavings,"") -> 6000 | F25: =IFERROR(DesiredRetirementIncome,"") -> 0 | G25: =IFERROR(PensionIncome,"") -> 0 | H25: =IFERROR(EndBalance,"") -> 75467.355 | I25: =IFERROR(Balance_Under,"") -> 63496.772 | J25: =IFERROR(Interest_Under,"") -> 2539.8709 | K25: =IFERROR(YearlySavings_Under,"") -> 6000 | L25: =IFERROR(DesiredRetirementIncome,"") -> 0 | M25: =IFERROR(PensionIncome_Under,"") -> 0 | N25: =IFERROR(EndBalance,"") -> 72036.643 | O25: =IFERROR(Balance_Over,"") -> 68947.896 | P25: =IFERROR(Interest_Over,"") -> 4136.8738 | Q25: =IFERROR(YearlySavings_Over,"") -> 6000 | R25: =IFERROR(DesiredRetirementIncome,"") -> 0 | S25: =IFERROR(PensionIncome_Over,"") -> 0 | T25: =IFERROR(EndBalance,"") -> 79084.77 | W25: =IF(Calculations!A25<DesiredRetirementAge,H25,NA()) -> 75467.355 | X25: =IF(Calculations!A25>=(DesiredRetirementAge-1),H25,NA()) -> #N/A | AA25: =T25-N25 -> 7048.1269
A26: =IFERROR(Age,"") -> 35 | B26: =IFERROR(Salary,"") -> 55231.106 | C26: =IFERROR(Balance,"") -> 75467.355 | D26: =IFERROR(Interest,"") -> 3773.3678 | E26: =IFERROR(YearlySavings,"") -> 6000 | F26: =IFERROR(DesiredRetirementIncome,"") -> 0 | G26: =IFERROR(PensionIncome,"") -> 0 | H26: =IFERROR(EndBalance,"") -> 85240.723 | I26: =IFERROR(Balance_Under,"") -> 72036.643 | J26: =IFERROR(Interest_Under,"") -> 2881.4657 | K26: =IFERROR(YearlySavings_Under,"") -> 6000 | L26: =IFERROR(DesiredRetirementIncome,"") -> 0 | M26: =IFERROR(PensionIncome_Under,"") -> 0 | N26: =IFERROR(EndBalance,"") -> 80918.108 | O26: =IFERROR(Balance_Over,"") -> 79084.77 | P26: =IFERROR(Interest_Over,"") -> 4745.0862 | Q26: =IFERROR(YearlySavings_Over,"") -> 6000 | R26: =IFERROR(DesiredRetirementIncome,"") -> 0 | S26: =IFERROR(PensionIncome_Over,"") -> 0 | T26: =IFERROR(EndBalance,"") -> 89829.856 | W26: =IF(Calculations!A26<DesiredRetirementAge,H26,NA()) -> 85240.723 | X26: =IF(Calculations!A26>=(DesiredRetirementAge-1),H26,NA()) -> #N/A | AA26: =T26-N26 -> 8911.7474
A27: =IFERROR(Age,"") -> 36 | B27: =IFERROR(Salary,"") -> 55783.417 | C27: =IFERROR(Balance,"") -> 85240.723 | D27: =IFERROR(Interest,"") -> 4262.0361 | E27: =IFERROR(YearlySavings,"") -> 6000 | F27: =IFERROR(DesiredRetirementIncome,"") -> 0 | G27: =IFERROR(PensionIncome,"") -> 0 | H27: =IFERROR(EndBalance,"") -> 95502.759 | I27: =IFERROR(Balance_Under,"") -> 80918.108 | J27: =IFERROR(Interest_Under,"") -> 3236.7243 | K27: =IFERROR(YearlySavings_Under,"") -> 6000 | L27: =IFERROR(DesiredRetirementIncome,"") -> 0 | M27: =IFERROR(PensionIncome_Under,"") -> 0 | N27: =IFERROR(EndBalance,"") -> 90154.833 | O27: =IFERROR(Balance_Over,"") -> 89829.856 | P27: =IFERROR(Interest_Over,"") -> 5389.7914 | Q27: =IFERROR(YearlySavings_Over,"") -> 6000 | R27: =IFERROR(DesiredRetirementIncome,"") -> 0 | S27: =IFERROR(PensionIncome_Over,"") -> 0 | T27: =IFERROR(EndBalance,"") -> 101219.65 | W27: =IF(Calculations!A27<DesiredRetirementAge,H27,NA()) -> 95502.759 | X27: =IF(Calculations!A27>=(DesiredRetirementAge-1),H27,NA()) -> #N/A | AA27: =T27-N27 -> 11064.814
A28: =IFERROR(Age,"") -> 37 | B28: =IFERROR(Salary,"") -> 56341.252 | C28: =IFERROR(Balance,"") -> 95502.759 | D28: =IFERROR(Interest,"") -> 4775.138 | E28: =IFERROR(YearlySavings,"") -> 6000 | F28: =IFERROR(DesiredRetirementIncome,"") -> 0 | G28: =IFERROR(PensionIncome,"") -> 0 | H28: =IFERROR(EndBalance,"") -> 106277.9 | I28: =IFERROR(Balance_Under,"") -> 90154.833 | J28: =IFERROR(Interest_Under,"") -> 3606.1933 | K28: =IFERROR(YearlySavings_Under,"") -> 6000 | L28: =IFERROR(DesiredRetirementIncome,"") -> 0 | M28: =IFERROR(PensionIncome_Under,"") -> 0 | N28: =IFERROR(EndBalance,"") -> 99761.026 | O28: =IFERROR(Balance_Over,"") -> 101219.65 | P28: =IFERROR(Interest_Over,"") -> 6073.1788 | Q28: =IFERROR(YearlySavings_Over,"") -> 6000 | R28: =IFERROR(DesiredRetirementIncome,"") -> 0 | S28: =IFERROR(PensionIncome_Over,"") -> 0 | T28: =IFERROR(EndBalance,"") -> 113292.83 | W28: =IF(Calculations!A28<DesiredRetirementAge,H28,NA()) -> 106277.9 | X28: =IF(Calculations!A28>=(DesiredRetirementAge-1),H28,NA()) -> #N/A | AA28: =T28-N28 -> 13531.8
... A115: =IFERROR(Age,"") | B115: =IFERROR(Salary,"") | C115: =IFERROR(Balance,"") | D115: =IFERROR(Interest,"") | E115: =IFERROR(YearlySavings,"") | F115: =IFERROR(DesiredRetirementIncome,"") | G115: =IFERROR(PensionIncome,"") | H115: =IFERROR(EndBalance,"") | I115: =IFERROR(Balance_Under,"") | J115: =IFERROR(Interest_Under,"") | K115: =IFERROR(YearlySavings_Under,"") | L115: =IFERROR(DesiredRetirementIncome,"") | M115: =IFERROR(PensionIncome_Under,"") | N115: =IFERROR(EndBalance,"") | O115: =IFERROR(Balance_Over,"") | P115: =IFERROR(Interest_Over,"") | Q115: =IFERROR(YearlySavings_Over,"") | R115: =IFERROR(DesiredRetirementIncome,"") | S115: =IFERROR(PensionIncome_Over,"") | T115: =IFERROR(EndBalance,"") | W115: =IF(Calculations!A115<DesiredRetirementAge,H115,NA()) -> #N/A | X115: =IF(Calculations!A115>=(DesiredRetirementAge-1),H115,NA()) | AA115: =T115-N115 -> #VALUE!
